half_orm_inspect/__init__.py
half_orm_inspect/cli_extension.py
half_orm_inspect-0.16.0.dist-info/licenses/LICENSE
half_orm_inspect-0.16.0.dist-info/METADATA
half_orm_inspect-0.16.0.dist-info/WHEEL
half_orm_inspect-0.16.0.dist-info/entry_points.txt
half_orm_inspect-0.16.0.dist-info/top_level.txt
half_orm_inspect-0.16.0.dist-info/RECORD
