Metadata-Version: 2.4
Name: half-orm-inspect
Version: 0.16.0
Summary: Database inspection extension for half-orm
Home-page: https://github.com/half-orm/half-orm-inspect
Author: half-orm Team
Author-email: contact@half-orm.org
Project-URL: Bug Reports, https://github.com/half-orm/half-orm-inspect/issues
Project-URL: Source, https://github.com/half-orm/half-orm-inspect
Project-URL: Documentation, https://half-orm.org/extensions/inspect
Keywords: half-orm,PostgreSQL,ORM,database,inspection,introspection
Classifier: Development Status :: 4 - Beta
Classifier: Intended Audience :: Developers
Classifier: License :: OSI Approved :: MIT License
Classifier: Programming Language :: Python :: 3
Classifier: Programming Language :: Python :: 3.7
Classifier: Programming Language :: Python :: 3.8
Classifier: Programming Language :: Python :: 3.9
Classifier: Programming Language :: Python :: 3.10
Classifier: Programming Language :: Python :: 3.11
Classifier: Programming Language :: Python :: 3.12
Classifier: Topic :: Database
Classifier: Topic :: Software Development :: Libraries :: Python Modules
Requires-Python: >=3.7
License-File: LICENSE
Requires-Dist: half_orm>=0.16
Requires-Dist: click>=7.0
Provides-Extra: dev
Requires-Dist: pytest>=6.0; extra == "dev"
Requires-Dist: pytest-cov; extra == "dev"
Requires-Dist: black; extra == "dev"
Requires-Dist: flake8; extra == "dev"
Provides-Extra: json
Dynamic: author
Dynamic: author-email
Dynamic: classifier
Dynamic: description
Dynamic: description-content-type
Dynamic: home-page
Dynamic: keywords
Dynamic: license-file
Dynamic: project-url
Dynamic: provides-extra
Dynamic: requires-dist
Dynamic: requires-python
Dynamic: summary
